daytona_api_client_async/__init__.py
daytona_api_client_async/api_client.py
daytona_api_client_async/api_response.py
daytona_api_client_async/configuration.py
daytona_api_client_async/exceptions.py
daytona_api_client_async/py.typed
daytona_api_client_async/rest.py
daytona_api_client_async/api/__init__.py
daytona_api_client_async/api/api_keys_api.py
daytona_api_client_async/api/docker_registry_api.py
daytona_api_client_async/api/object_storage_api.py
daytona_api_client_async/api/organizations_api.py
daytona_api_client_async/api/preview_api.py
daytona_api_client_async/api/runners_api.py
daytona_api_client_async/api/sandbox_api.py
daytona_api_client_async/api/snapshots_api.py
daytona_api_client_async/api/toolbox_api.py
daytona_api_client_async/api/users_api.py
daytona_api_client_async/api/volumes_api.py
daytona_api_client_async/api/workspace_api.py
daytona_api_client_async/models/__init__.py
daytona_api_client_async/models/account_provider.py
daytona_api_client_async/models/api_key_list.py
daytona_api_client_async/models/api_key_response.py
daytona_api_client_async/models/build_info.py
daytona_api_client_async/models/command.py
daytona_api_client_async/models/completion_context.py
daytona_api_client_async/models/completion_item.py
daytona_api_client_async/models/completion_list.py
daytona_api_client_async/models/create_api_key.py
daytona_api_client_async/models/create_build_info.py
daytona_api_client_async/models/create_docker_registry.py
daytona_api_client_async/models/create_linked_account.py
daytona_api_client_async/models/create_organization.py
daytona_api_client_async/models/create_organization_invitation.py
daytona_api_client_async/models/create_organization_quota.py
daytona_api_client_async/models/create_organization_role.py
daytona_api_client_async/models/create_runner.py
daytona_api_client_async/models/create_sandbox.py
daytona_api_client_async/models/create_session_request.py
daytona_api_client_async/models/create_snapshot.py
platon_daytona_api_client_async-0.1.5.dist-info/licenses/LICENSE
platon_daytona_api_client_async-0.1.5.dist-info/METADATA
platon_daytona_api_client_async-0.1.5.dist-info/WHEEL
platon_daytona_api_client_async-0.1.5.dist-info/top_level.txt
platon_daytona_api_client_async-0.1.5.dist-info/RECORD
